{
  "pageCacheStats" : {
    "cachedChannelsStatistics" : {
      "hit" : 7038,
      "miss" : 0,
      "load" : 113,
      "capacity" : 400
    },
    "uncachedFileAccess" : 284,
    "maxRegisteredFiles" : 642,
    "maxCacheSizeInBytes" : 418488320,
    "pageHit" : 27288,
    "pageFastCacheHit" : 8144848,
    "pageMiss" : 0,
    "pageLoad" : 5641,
    "disposedBuffers" : 3952,
    "capacityInBytes" : 524288000
  },
  "vfsStorageStats" : {
    "statsPerEnumerator" : {
      "contentHashes.dat" : {
        "collisions" : 0,
        "values" : 23,
        "dataFileSizeInBytes" : 460,
        "storageSizeInBytes" : 96,
        "btreeStatistics" : {
          "pages" : 1,
          "elements" : 23,
          "height" : 1,
          "moves" : 0,
          "leafPages" : 1,
          "maxSearchStepsInRequest" : 0,
          "searchRequests" : 46,
          "searchSteps" : 0,
          "pageCapacity" : 32768,
          "sizeInBytes" : 32768
        }
      },
      "names.dat" : {
        "collisions" : 22,
        "values" : 224664,
        "dataFileSizeInBytes" : 6543918,
        "storageSizeInBytes" : 304,
        "btreeStatistics" : {
          "pages" : 75,
          "elements" : 224652,
          "height" : 2,
          "moves" : 1320,
          "leafPages" : 74,
          "maxSearchStepsInRequest" : 102,
          "searchRequests" : 803839,
          "searchSteps" : 1391357,
          "pageCapacity" : 32768,
          "sizeInBytes" : 2457600
        }
      }
    }
  },
  "indexStorageStats" : {
    "indexStoragesStats" : { }
  }
}